{"formautofill@mozilla.org":{"permissions":["internal:svgContextPropertiesAllowed","internal:privateBrowsingAllowed"],"origins":[]},"pictureinpicture@mozilla.org":{"permissions":["internal:svgContextPropertiesAllowed","internal:privateBrowsingAllowed"],"origins":[]},"screenshots@mozilla.org":{"permissions":["internal:svgContextPropertiesAllowed","internal:privateBrowsingAllowed"],"origins":[]},"webcompat@mozilla.org":{"permissions":["internal:svgContextPropertiesAllowed","internal:privateBrowsingAllowed"],"origins":[]},"default-theme@mozilla.org":{"permissions":["internal:svgContextPropertiesAllowed","internal:privateBrowsingAllowed"],"origins":[]},"addons-search-detection@mozilla.com":{"permissions":["internal:svgContextPropertiesAllowed","internal:privateBrowsingAllowed"],"origins":[]},"wikipedia@search.mozilla.org":{"permissions":["internal:svgContextPropertiesAllowed","internal:privateBrowsingAllowed"],"origins":[]},"ddg@search.mozilla.org":{"permissions":["internal:svgContextPropertiesAllowed","internal:privateBrowsingAllowed"],"origins":[]},"uBlock0@raymondhill.net":{"permissions":["internal:privateBrowsingAllowed"],"origins":[]},"frankerfacez@frankerfacez.com":{"permissions":["internal:privateBrowsingAllowed"],"origins":[]},"jid1-xUfzOsOFlzSOXg@jetpack":{"permissions":["internal:privateBrowsingAllowed"],"origins":["https://*.redd.it/*","https://xkcd.com/*","https://publish.twitter.com/*","https://backend.deviantart.com/*","https://api.tumblr.com/*","https://api.steampowered.com/*"]}}